<?xml version='1.0' encoding='UTF-8'?>
<DEFECTS><DEFECT><SFA><FILEPATH>c:\users\diamantinosilva\documents\github\linkplanner\sdf\eavesdropper_study\</FILEPATH><FILENAME>eavesdropper_study_sdf.cpp</FILENAME><LINE>17</LINE><COLUMN>8</COLUMN></SFA><DEFECTCODE>6262</DEFECTCODE><DESCRIPTION>Function uses '59240' bytes of stack:  exceeds /analyze:stacksize '16384'.  Consider moving some data to heap.</DESCRIPTION><FUNCTION>main</FUNCTION><DECORATED>main</DECORATED><FUNCLINE>17</FUNCLINE><PATH/></DEFECT></DEFECTS>